django_richtexteditor/__init__.py
django_richtexteditor/fields.py
django_richtexteditor/settings.py
django_richtexteditor/utils.py
django_richtexteditor/widgets.py
django_richtexteditor/static/js/django_richtexteditor/ckeditor/v4/basic.js
django_richtexteditor/static/js/django_richtexteditor/ckeditor/v4/full-all.js
django_richtexteditor/static/js/django_richtexteditor/ckeditor/v4/full.js
django_richtexteditor/static/js/django_richtexteditor/ckeditor/v4/standard-all.js
django_richtexteditor/static/js/django_richtexteditor/ckeditor/v4/standard.js
django_richtexteditor/static/js/django_richtexteditor/ckeditor/v5/balloon-block.js
django_richtexteditor/static/js/django_richtexteditor/ckeditor/v5/balloon.js
django_richtexteditor/static/js/django_richtexteditor/ckeditor/v5/classic.js
django_richtexteditor/static/js/django_richtexteditor/ckeditor/v5/decoupled-document.js
django_richtexteditor/static/js/django_richtexteditor/ckeditor/v5/inline.js
django_richtexteditor/templates/django_richtexteditor/richtextarea.html
django_richtexteditor-0.0.1.dev3.dist-info/LICENSE
django_richtexteditor-0.0.1.dev3.dist-info/METADATA
django_richtexteditor-0.0.1.dev3.dist-info/WHEEL
django_richtexteditor-0.0.1.dev3.dist-info/top_level.txt
django_richtexteditor-0.0.1.dev3.dist-info/RECORD
